paintmind/__init__.py
paintmind/config.py
paintmind/encoder.py
paintmind/factory.py
paintmind/pipeline.py
paintmind/reconstruct.py
paintmind/version.py
paintmind/stage1/__init__.py
paintmind/stage1/discriminator.py
paintmind/stage1/layers.py
paintmind/stage1/quantize.py
paintmind/stage1/vqmodel.py
paintmind/stage2/__init__.py
paintmind/stage2/transformer.py
paintmind/utils/__init__.py
paintmind/utils/datasets.py
paintmind/utils/lr_scheduler.py
paintmind/utils/trainer.py
paintmind/utils/transform.py
paintmind-0.0.dist-info/LICENSE
paintmind-0.0.dist-info/METADATA
paintmind-0.0.dist-info/WHEEL
paintmind-0.0.dist-info/top_level.txt
paintmind-0.0.dist-info/RECORD
